{
    "example6942012345": {
        "1": {
            "id": "004",
            "name": null,
            "species": "Charmander",
            "level": 5,
            "types": [
                "Fire"
            ],
            "stats": {
                "Current HP": 23,
                "HP": 23,
                "Attack": 13,
                "Defense": 12,
                "Speed": 16,
                "Special": 14
            },
            "moves": {
                "move1": "Growl",
                "move2": "Scratch",
                "move3": null,
                "move4": null
            },
            "iv": {
                "HP": 13,
                "Attack": 1,
                "Defense": 1,
                "Speed": 14,
                "Special": 11
            }
        },
        "2": null,
        "3": null,
        "4": null,
        "5": null,
        "6": null
    }
}
